pyquake/__init__.py
pyquake/pyquake.py
pyquake-1.0.5.dist-info/LICENSE
pyquake-1.0.5.dist-info/METADATA
pyquake-1.0.5.dist-info/WHEEL
pyquake-1.0.5.dist-info/top_level.txt
pyquake-1.0.5.dist-info/RECORD
