Metadata-Version: 2.1
Name: pyquake
Version: 1.0.5
Summary: A package enabling the synthesis of seismic audio.
Home-page: https://github.com/cooperbarth/PyQuake
Author: Cooper Barth
Author-email: cooperfbarth@gmail.com
License: UNKNOWN
Platform: UNKNOWN
Classifier: Programming Language :: Python :: 3
Classifier: License :: OSI Approved :: MIT License
Classifier: Operating System :: OS Independent
Requires-Dist: numpy
Requires-Dist: scipy
Requires-Dist: mpu
